gradio_mcp_tools_visualizer/__init__.py
gradio_mcp_tools_visualizer/mcp_tools_visualizer.py
gradio_mcp_tools_visualizer/mcp_tools_visualizer.pyi
gradio_mcp_tools_visualizer/templates/component/index.js
gradio_mcp_tools_visualizer/templates/component/style.css
gradio_mcp_tools_visualizer/templates/example/index.js
gradio_mcp_tools_visualizer/templates/example/style.css
gradio_mcp_tools_visualizer-0.0.4.dist-info/METADATA
gradio_mcp_tools_visualizer-0.0.4.dist-info/WHEEL
gradio_mcp_tools_visualizer-0.0.4.dist-info/RECORD
